lyrics_extractor/__init__.py
lyrics_extractor/hello.py
lyrics_extractor/lyrics.py
lyrics_extractor/settings.py
lyrics_extractor-3.0.1.dist-info/LICENSE
lyrics_extractor-3.0.1.dist-info/METADATA
lyrics_extractor-3.0.1.dist-info/WHEEL
lyrics_extractor-3.0.1.dist-info/entry_points.txt
lyrics_extractor-3.0.1.dist-info/top_level.txt
lyrics_extractor-3.0.1.dist-info/RECORD
