Metadata-Version: 2.1
Name: lyrics_extractor
Version: 3.0.1
Summary: Get Lyrics for any songs by just passing in the song name (spelled or misspelled) in less than 2 seconds using this awesome Python Library.
Home-page: https://github.com/Techcatchers/PyLyrics-Extractor
Author: Rishabh Agrawal
Author-email: rishabha.1999@gmail.com
License: MIT
Platform: UNKNOWN
Classifier: License :: OSI Approved :: MIT License
Classifier: Programming Language :: Python :: 3
Classifier: Programming Language :: Python :: 3.5
Classifier: Programming Language :: Python :: 3.6
Classifier: Programming Language :: Python :: 3.7
Provides-Extra: dev
